README.md
setup.py
calculator_module/__init__.py
calculator_module/calculator.py
calculatorvb_packagevb.egg-info/PKG-INFO
calculatorvb_packagevb.egg-info/SOURCES.txt
calculatorvb_packagevb.egg-info/dependency_links.txt
calculatorvb_packagevb.egg-info/top_level.txt
tests/__init__.py
tests/tests_calculator.py