Metadata-Version: 2.1
Name: calculatorvb-packagevb
Version: 1.0.0
Summary: A simple calculator package for basic math calculations
Author: Vytautas Bunevičius
Author-email: bunvytt@gmail.com
License: MIT
